txt/OStxt.py
txt/__init__.py
txt/txt.py
txt/version.py
txt/numtxt/__init__.py
txt/numtxt/numtxt.py
txt/password/__init__.py
txt/password/passlib.py
txt/password/password.py
txt/plot/__init__.py
txt/plot/plot.py
txt_sky-1.2.2.dist-info/LICENSE
txt_sky-1.2.2.dist-info/METADATA
txt_sky-1.2.2.dist-info/WHEEL
txt_sky-1.2.2.dist-info/top_level.txt
txt_sky-1.2.2.dist-info/RECORD
