Metadata-Version: 2.1
Name: txt-sky
Version: 1.2.2
Summary: A package for writing txt
Author-email: Sky Vega Yang <xjgis@126.com>
Classifier: Programming Language :: Python :: 3
Classifier: License :: OSI Approved :: MIT License
Classifier: Operating System :: OS Independent
Requires-Python: >=3.8
License-File: LICENSE
